fsspec_reference_maker/__init__.py
fsspec_reference_maker/_version.py
fsspec_reference_maker/combine.py
fsspec_reference_maker/fits.py
fsspec_reference_maker/grib2.py
fsspec_reference_maker/hdf.py
fsspec_reference_maker/utils.py
fsspec_reference_maker-0.0.3.dist-info/LICENSE
fsspec_reference_maker-0.0.3.dist-info/METADATA
fsspec_reference_maker-0.0.3.dist-info/WHEEL
fsspec_reference_maker-0.0.3.dist-info/top_level.txt
fsspec_reference_maker-0.0.3.dist-info/RECORD
