Metadata-Version: 2.1
Name: fsspec-reference-maker
Version: 0.0.3
Summary: Functions to make reference descriptions for ReferenceFileSystem
Home-page: https://github.com/intake/fsspec-reference-maker
Author: Martin Durant
Author-email: martin.durant@utoronto.ca
License: MIT
Platform: UNKNOWN
Requires-Python: >=3.7
Requires-Dist: fsspec
Requires-Dist: ujson
